tex_table.py
tex_table-1.2.dist-info/WHEEL
tex_table-1.2.dist-info/METADATA
tex_table-1.2.dist-info/RECORD
