Metadata-Version: 2.1
Name: tex_table
Version: 1.2
Summary: A package to convert a pandas DataFrame to a LaTeX table.
Author-email: Dan DeGenaro <drd92@georgetown.edu>
Requires-Python: >=3.11
Classifier: Programming Language :: Python :: 3
Classifier: License :: OSI Approved :: MIT License
Classifier: Operating System :: OS Independent
Requires-Dist: pandas
Requires-Dist: numpy
Requires-Dist: requests
Project-URL: Homepage, https://github.com/dan-the-meme-man/tex-table
Project-URL: Issues, https://github.com/dan-the-meme-man/tex-table/issues
